README.txt
bootstrap.py
buildout.cfg
setup.cfg
setup.py
docs/HISTORY.txt
docs/INSTALL.txt
docs/LICENSE.GPL
docs/LICENSE.txt
iservices/__init__.py
iservices.controlpanel.egg-info/PKG-INFO
iservices.controlpanel.egg-info/SOURCES.txt
iservices.controlpanel.egg-info/dependency_links.txt
iservices.controlpanel.egg-info/entry_points.txt
iservices.controlpanel.egg-info/namespace_packages.txt
iservices.controlpanel.egg-info/not-zip-safe
iservices.controlpanel.egg-info/requires.txt
iservices.controlpanel.egg-info/top_level.txt
iservices/controlpanel/__init__.py
iservices/controlpanel/api.py
iservices/controlpanel/api_usage.rst
iservices/controlpanel/configure.zcml
iservices/controlpanel/controlpanel.py
iservices/controlpanel/functional_test.rst
iservices/controlpanel/interfaces.py
iservices/controlpanel/tests.py
iservices/controlpanel/browser/__init__.py
iservices/controlpanel/browser/colophon.pt
iservices/controlpanel/browser/configure.zcml
iservices/controlpanel/browser/customcss.py
iservices/controlpanel/browser/footer.pt
iservices/controlpanel/browser/interfaces.py
iservices/controlpanel/browser/viewlets.py
iservices/controlpanel/profiles/default/controlpanel.xml
iservices/controlpanel/profiles/default/cssregistry.xml
iservices/controlpanel/profiles/default/metadata.xml
iservices/controlpanel/profiles/default/registry.xml