Metadata-Version: 1.0
Name: iservices.controlpanel
Version: 0.3.1
Summary: A generic control panel for themers and site integrators
Home-page: https://github.com/collective/iservices.controlpanel
Author: Noe Nieto
Author-email: noe@iservices.com.mx
License: GPL
Keywords: plone theme control panel
Platform: UNKNOWN
Classifier: Development Status :: 4 - Beta
Classifier: Intended Audience :: Developers
Classifier: License :: OSI Approved
Classifier: Topic :: Software Development :: Libraries :: Python Modules
Classifier: Intended Audience :: System Administrators
Classifier: Framework :: Plone
Classifier: Programming Language :: Python
